tests/__init__.py
tests/int/__init__.py
tests/int/test_builder.py
tests/int/backends/__init__.py
tests/int/backends/test_espeak_ng.py
tests/int/backends/test_festival.py
tests/unit/__init__.py
tests/unit/test_init.py
tests/unit/test_restorer.py
tests/unit/backends/__init__.py
tests/unit/backends/test_base.py
transcriber_wrapper/__init__.py
transcriber_wrapper/builder.py
transcriber_wrapper/exceps.py
transcriber_wrapper/restorer.py
transcriber_wrapper/backends/__init__.py
transcriber_wrapper/backends/base.py
transcriber_wrapper/backends/espeak_ng.py
transcriber_wrapper/backends/exceps.py
transcriber_wrapper/backends/festival.py
transcriber_wrapper/dealers/InternationalPhoneticAlphabet.py
transcriber_wrapper/dealers/__init__.py
transcriber_wrapper/support/__init__.py
transcriber_wrapper/support/subprocess_utils.py
transcriber_wrapper-1.2.1.dist-info/LICENSE
transcriber_wrapper-1.2.1.dist-info/METADATA
transcriber_wrapper-1.2.1.dist-info/WHEEL
transcriber_wrapper-1.2.1.dist-info/top_level.txt
transcriber_wrapper-1.2.1.dist-info/RECORD
