Metadata-Version: 2.1
Name: transcriber-wrapper
Version: 1.2.1
Summary: A wrapper of well-known translators that transform text into its phonetic transcription
Home-page: https://github.com/willianantunes/transcriber-wrapper
Author: Willian Antunes
Author-email: willian.lima.antunes@gmail.com
License: GPL3
Project-URL: Bug Tracker, https://github.com/willianantunes/transcriber-wrapper/issues
Keywords: linguistics ipa transcriber phonetics pronunciation dictionary
Platform: UNKNOWN
Classifier: Programming Language :: Python :: 3.9
Classifier: License :: OSI Approved :: GNU General Public License v3 or later (GPLv3+)
Classifier: Intended Audience :: Developers
Classifier: Operating System :: OS Independent
Requires-Python: >=3.9
Requires-Dist: pyparsing (~=2.4)
